{
  "label": "Одна арка по одной инструкции",
  "wizardPages": [
    {
      "id": "instructions",
      "title": "Инструкции",
      "fields": [
        {
          "name": "instructions",
          "type": "textarea",
          "label": "Основная идея рассказа",
          "description": "Опишите, какой рассказ сгенерировать",
          "placeholder": "Описание стиля, персонажей, что происходит в рассказе"
        }
      ]
    }
  ],
  "plan": {
    "nodes": [
      {
        "id": 1,
        "title": "Основная инструкция",
        "type": "text",
        "content": ["${instructions}"]
      },
      {
        "id": 2,
        "title": "Стиль",
        "type": "text",
        "aiUserInstructions": [
          "## Инструкция (для справки)",
          "```",
          "{{Основная инструкция}}",
          "```",
          "",
          "## Что надо сделать",
          "",
          "Погугли, подумай и сформулируй, правила стиля для рассказа, который должен быть написан по инструкции выше.",
          "Пиши на русском языке. Требование к объёму и/или числу слов не указывай. Источники не указывай. Пиши подробно (1450-1550 слов)."
        ],
        "inputs": [
          {
            "sourceNodeId": 1,
            "type": "text"
          }
        ]
      },
      {
        "id": 3,
        "title": "Персонажи (черновик)",
        "type": "text",
        "aiUserInstructions": [
          "## Инструкция (для справки)",
          "```",
          "{{Основная инструкция}}",
          "```",
          "",
          "## Стиль (для справки)",
          "```",
          "{{Стиль}}",
          "```",
          "",
          "## Что надо сделать",
          "",
          "Опиши профили основных персонажей, которые будут использованы в создании рассказа. Источники не указывай. Пиши подробно (1450-1550 слов)."
        ],
        "inputs": [
          {
            "sourceNodeId": 1,
            "type": "text"
          },
          {
            "sourceNodeId": 2,
            "type": "text"
          }
        ]
      },
      {
        "id": 4,
        "title": "Персонажи",
        "type": "fix-problems",
        "nodeTypeSettings": {
          "sourceNodeIdToFix": 3,
          "maxIterations": 5,
          "minSeverityToFix": 30,
          "foundProblemsTemplate": "{{Found Problems}}",
          "aiUserInstructionsToFindProblems": [
            "Возьми профили персонажей и найди в них любые ошибки (включая, но не ограничиваясь, логические, фактически, стилистические, соответствие русскому языку). Не менее 10 ошибок.",
            "",
            "## Стиль (для справки)",
            "```",
            "{{Стиль}}",
            "```",
            "",
            "## Профили персонажей (для поиска ошибок)",
            "```",
            "{{Персонажи (черновик)}}",
            "```"
          ],
          "aiUserInstructionsToFixProblems": [
            "Возьми профили персонажей и поправь в них найденные в нём ошибки, указанные далее. Выводи сразу и только поправленные профили (как простой текст).",
            "",
            "## Стиль (для справки)",
            "```",
            "{{Стиль}}",
            "```",
            "",
            "## Профили персонажей (для поиска ошибок)",
            "```",
            "{{Персонажи (черновик)}}",
            "```",
            "",
            "## Список ошибок для исправления",
            "```",
            "{{Found Problems}}",
            "```"
          ]
        },
        "inputs": [
          {
            "sourceNodeId": 1,
            "type": "text"
          },
          {
            "sourceNodeId": 2,
            "type": "text"
          },
          {
            "sourceNodeId": 3,
            "type": "text"
          }
        ]
      }
    ]
  }
}
